argvparse/__init__.py
argvparse/parser.py
argvparse-1.0.dist-info/LICENSE
argvparse-1.0.dist-info/METADATA
argvparse-1.0.dist-info/WHEEL
argvparse-1.0.dist-info/top_level.txt
argvparse-1.0.dist-info/RECORD
